docs/__init__.py
docs/urls.py
docs/views.py
docs/tests/__init__.py
docs/tests/runtests.py
docs/tests/test_views.py
docs/tests/urls.py
docs/tests/test_docs/index.html
docs/tests/test_docs/sub_dir/index.html
django_docs-0.3.3.dist-info/AUTHORS
django_docs-0.3.3.dist-info/LICENSE
django_docs-0.3.3.dist-info/METADATA
django_docs-0.3.3.dist-info/WHEEL
django_docs-0.3.3.dist-info/top_level.txt
django_docs-0.3.3.dist-info/RECORD
