Metadata-Version: 2.1
Name: django-docs
Version: 0.3.3
Summary: Allows to serve Sphinx generated docs from django.
Home-page: https://github.com/littlepea/django-docs
Author: Evgeny Demchenko
Author-email: little_pea@list.ru
License: BSD
Classifier: Topic :: Internet :: WWW/HTTP :: Dynamic Content
Classifier: Intended Audience :: Developers
Classifier: Programming Language :: Python
Classifier: Programming Language :: Python :: 3.6
Classifier: Programming Language :: Python :: 3.7
Classifier: Programming Language :: Python :: 3.8
Classifier: Programming Language :: Python :: 3.9
Classifier: Programming Language :: Python :: 3.10
Classifier: Programming Language :: Python :: 3.11
Classifier: Framework :: Django
Classifier: Development Status :: 4 - Beta
Classifier: Operating System :: OS Independent
License-File: LICENSE
License-File: AUTHORS
